libastr/__init__.py
libastr/client.py
libastr/exceptions.py
libastr/logger.py
libastr/resources.py
libastr-1.1.0.dist-info/METADATA
libastr-1.1.0.dist-info/RECORD
libastr-1.1.0.dist-info/WHEEL
libastr-1.1.0.dist-info/top_level.txt
