Metadata-Version: 2.1
Name: libastr
Version: 1.1.0
Summary: A Python library to interact with ASTR servers.
Home-page: https://github.com/aldebaran/lib-python-astr
Author: Softbank Robotics Europe
Author-email: UNKNOWN
License: MPL-2.0
Platform: UNKNOWN
Classifier: Programming Language :: Python :: 3
Classifier: License :: OSI Approved :: Mozilla Public License 2.0 (MPL 2.0)
Classifier: Operating System :: OS Independent
